dctdevtools/__init__.py
dctdevtools/__main__.py
dctdevtools/odoo_modules.py
dctdevtools-0.3.data/scripts/dctdevtools
dctdevtools-0.3.dist-info/METADATA
dctdevtools-0.3.dist-info/WHEEL
dctdevtools-0.3.dist-info/entry_points.txt
dctdevtools-0.3.dist-info/top_level.txt
dctdevtools-0.3.dist-info/RECORD
