Metadata-Version: 2.1
Name: dctdevtools
Version: 0.3
Summary: DCT Development Tools
Home-page: UNKNOWN
Author: Max Dinh
Author-email: max.dinh@dctsolutions.io
License: MIT
Platform: UNKNOWN
